database_infrastructure_local/Connector.py
database_infrastructure_local/__init__.py
database_infrastructure_local/constants.py
database_infrastructure_local/constants_tests.py
database_infrastructure_local/generic_crud_abstract.py
database_infrastructure_local/number_generator.py
database_infrastructure_local/point.py
database_infrastructure_local/to_sql_interface.py
database_infrastructure_local-0.1.6.dist-info/METADATA
database_infrastructure_local-0.1.6.dist-info/WHEEL
database_infrastructure_local-0.1.6.dist-info/top_level.txt
database_infrastructure_local-0.1.6.dist-info/RECORD
