Metadata-Version: 2.4
Name: database-infrastructure-local
Version: 0.1.6
Home-page: https://github.com/circles-zone/database-infrastructure-local-python-package
Author: Circles
Author-email: info@circlez.ai
Classifier: Programming Language :: Python :: 3
Classifier: Operating System :: OS Independent
Requires-Dist: mysql-connector-python>=8.5.0
Requires-Dist: python-sdk-remote>=0.0.93
Requires-Dist: logger-local>=0.0.170
Dynamic: author
Dynamic: author-email
Dynamic: classifier
Dynamic: description
Dynamic: description-content-type
Dynamic: home-page
Dynamic: requires-dist
